youqu3/__init__.py
youqu3/__version__.py
youqu3/asserts.py
youqu3/cli.py
youqu3/envx.py
youqu3/init.py
youqu3/plugin.py
youqu3/py2csv.py
youqu3/remote.py
youqu3/run.py
youqu3/skipif.py
youqu3/utils.py
youqu3/_setting/__init__.py
youqu3/_setting/_dynamic.py
youqu3/_setting/_setting.py
youqu3/tpl/.env-tpl
youqu3/tpl/.gitignore-tpl
youqu3/tpl/README.md-tpl
youqu3/tpl/config.py-tpl
youqu3/tpl/conftest.py-tpl
youqu3/tpl/mycase.csv-tpl
youqu3/tpl/pytest.ini-tpl
youqu3/tpl/requirements.txt-tpl
youqu3/tpl/ruff.toml-tpl
youqu3/tpl/case/__init__.py-tpl
youqu3/tpl/case/base_case.py-tpl
youqu3/tpl/case/test_mycase_001.py-tpl
youqu3/tpl/case/test_mycase_002.py-tpl
youqu3/tpl/case/assert_res/README.md
youqu3/tpl/method/${app_name}_method.py-tpl
youqu3/tpl/method/assert_method.py-tpl
youqu3/tpl/method/base_method.py-tpl
youqu3/tpl/method/image_res/README.md
youqu3/tpl/method/static_res/README.md
youqu3_framework-3.2.4.dist-info/METADATA
youqu3_framework-3.2.4.dist-info/WHEEL
youqu3_framework-3.2.4.dist-info/entry_points.txt
youqu3_framework-3.2.4.dist-info/licenses/LICENSE
youqu3_framework-3.2.4.dist-info/RECORD
