Metadata-Version: 2.4
Name: youqu3-framework
Version: 3.2.4
Summary: Next-Gen Linux Autotest Framework
Author-email: wangpeng <781757836@qq.com>
License: GPL2.0
License-File: LICENSE
Requires-Python: >=3.6
Requires-Dist: allure-pytest
Requires-Dist: click
Requires-Dist: funnylog2
Requires-Dist: nocmd
Requires-Dist: pexpect
Requires-Dist: pytest-rerunfailures
Requires-Dist: pytest-timeout
Provides-Extra: gui
Requires-Dist: pylinuxauto; extra == 'gui'
Requires-Dist: pytest-record-video; extra == 'gui'
Requires-Dist: youqu-html-rpc; extra == 'gui'
Provides-Extra: html
Requires-Dist: youqu-html; extra == 'html'
Provides-Extra: html-rpc
Requires-Dist: youqu-html-rpc; extra == 'html-rpc'
Provides-Extra: http
Requires-Dist: requests; extra == 'http'
Requires-Dist: youqu-html-rpc; extra == 'http'
Provides-Extra: webui
Requires-Dist: playwright; extra == 'webui'
Requires-Dist: pytest-record-video; extra == 'webui'
Requires-Dist: youqu-html-rpc; extra == 'webui'
